Metadata-Version: 2.1
Name: TriGeneI
Version: 0.1
Summary: TGMI network inference using Python
Home-page: https://github.com/Hua-CM/TGMI
Author: Zhongyi Hua
Author-email: njbxhzy@hotmail.com
License: UNKNOWN
Platform: UNKNOWN
Classifier: Programming Language :: Python :: 3
Classifier: License :: OSI Approved :: GNU General Public License v3 or later (GPLv3+)
Classifier: Operating System :: OS Independent
Requires-Python: >=3
License-File: LICENSE
